[
    {
        "text": "Being broke at 30 starts at 20",
        "timestamp": "2024-10-15T15:47:08.000Z",
        "user_handle": "WealthSquad Chris ",
        "profile_image_url": "",
        "retweets": 14000,
        "likes": 103000,
        "tweet_images": [],
        "tweet_videos": []
    },
    {
        "text": "เฮกันเลย! ฟันธงแล้ว “รถไฟฟ้า 20 บาท”  ตลอดสาย ตลอดทุกเส้นทาง ไม่มีเก็บเพิ่มแน่นอน  รอนั่งกันเลยยาวๆ ตั้งแต่ต้นสายยันปลายสายก็ 20 บาท  โครงการนี้มีวัตถุประสงค์เพื่อรณรงค์ให้ทุกคนใช้ #รถไฟฟ้า กันมากขึ้น\nอ้างอิง >> https://buff.ly/4dPVb5t\n#SaleHere #เซลเฮียร์ #รถไฟฟ้า20บาท",
        "timestamp": "2024-10-16T08:10:01.000Z",
        "user_handle": "Sale Here - อะไรลดเรารู้",
        "profile_image_url": "",
        "retweets": 14000,
        "likes": 3000,
        "tweet_images": [
            "https://pbs.twimg.com/media/GZ_02v9XMAAaXCN?format=jpg&name=small"
        ],
        "tweet_videos": []
    },
    {
        "text": " 20 years ago today, Messi made his official debut for Barça.  \n\n Join us as we take a journey through his most unforgettable matches.",
        "timestamp": "2024-10-16T10:04:04.000Z",
        "user_handle": "FC Barcelona",
        "profile_image_url": "",
        "retweets": 3400,
        "likes": 21000,
        "tweet_images": [
            "https://pbs.twimg.com/media/GaANKmMXIAArwV_?format=jpg&name=small"
        ],
        "tweet_videos": []
    },
    {
        "text": " FLASH | Accusé de viol par une jeune femme, Kylian Mbappé aurait privatisé la boîte de nuit « V » à Stockholm. Selon la presse suédoise, entre 20 et 30 personnes, principalement des jeunes femmes suédoises, étaient présentes. Les convives auraient été priés de laisser leurs",
        "timestamp": "2024-10-16T08:42:25.000Z",
        "user_handle": "Cerfia",
        "profile_image_url": "",
        "retweets": 1500,
        "likes": 12000,
        "tweet_images": [
            "https://pbs.twimg.com/media/GZ_8RH2WoAAg58M?format=jpg&name=small"
        ],
        "tweet_videos": []
    },
    {
        "text": "The cover for the upcoming Hunger Games book ‘SUNRISE ON THE REAPING’ has been released.\n\nSet during the Second Quarter Quell, won by Haymitch Abernathy.\n\nIn theaters November 20, 2026.",
        "timestamp": "2024-10-16T12:26:02.000Z",
        "user_handle": "Film Updates",
        "profile_image_url": "",
        "retweets": 944,
        "likes": 3600,
        "tweet_images": [
            "https://pbs.twimg.com/media/GaAvcs8WMAA9SvL?format=jpg&name=small"
        ],
        "tweet_videos": []
    },
    {
        "text": "Chudai tushy mood",
        "timestamp": "2024-10-16T10:06:35.000Z",
        "user_handle": "Hoàng Bảo Trân",
        "profile_image_url": "",
        "retweets": 932,
        "likes": 5000,
        "tweet_images": [],
        "tweet_videos": [
            "https://video.twimg.com/amplify_video/1846406460273840128/vid/avc1/1280x720/RmN5wa4wLNG1LhSu.mp4?tag=14"
        ]
    },
    {
        "text": "[緊急地震速報] 17:54:14現在\n第7報(終) 予報\n発生時刻：17:53:20\n震央情報：茨城県南部\n震源情報：36.1N 139.9E 50km\n地震規模：M4.3 最大震度：3\n予想震度：1.8 猶予時間：主要動 到達",
        "timestamp": "2024-10-16T08:54:15.000Z",
        "user_handle": "地震速報",
        "profile_image_url": "",
        "retweets": 557,
        "likes": 567,
        "tweet_images": [
            "https://pbs.twimg.com/media/GZ_--tCbgAA8jic?format=png&name=small"
        ],
        "tweet_videos": []
    },
    {
        "text": "England have just appointed the best knockout competition tactician in world football as their manager. His last 4 Champions League runs from 2019/20, 2020/21, 2021/22, 2023/24 (1 CL win, 1 final, 1 semi-final where he was let down by a GK error and 1 quarter-final where he won",
        "timestamp": "2024-10-16T08:58:22.000Z",
        "user_handle": "Premier League Panel",
        "profile_image_url": "",
        "retweets": 504,
        "likes": 4300,
        "tweet_images": [
            "https://pbs.twimg.com/media/GZ_9pgxXgAARDJa?format=jpg&name=small"
        ],
        "tweet_videos": []
    },
    {
        "text": "Miss Universe Türkiye 2024 güzeli, 20 yaşındaki Ayliz Duman seçildi.",
        "timestamp": "2024-10-16T07:51:09.000Z",
        "user_handle": "DarkWeb Haber",
        "profile_image_url": "https://pbs.twimg.com/media/GZ_wdvZXoAAwW4O?format=jpg&name=small",
        "retweets": 343,
        "likes": 13000,
        "tweet_images": [
            "https://pbs.twimg.com/media/GZ_wdvZXoAAwW4O?format=jpg&name=small",
            "https://pbs.twimg.com/media/GZ_weYvXwAAgZLd?format=jpg&name=small"
        ],
        "tweet_videos": []
    },
    {
        "text": "JUST IN:  Pro-#Bitcoin Donald Trump takes the biggest lead in the election so far, up by 20.2% in the odds: Polymarket",
        "timestamp": "2024-10-16T12:32:10.000Z",
        "user_handle": "Bitcoin Magazine",
        "profile_image_url": "",
        "retweets": 330,
        "likes": 1800,
        "tweet_images": [
            "https://pbs.twimg.com/media/GaAw2vDX0AAnHN6?format=jpg&name=small"
        ],
        "tweet_videos": []
    },
    {
        "text": "Earlier this evening, invading Israeli forces assassinated the 20 year old resistance fighter Karim Jabarin in Jenin Camp, occupied West Bank, while they were besieging him in his home.",
        "timestamp": "2024-10-15T21:04:14.000Z",
        "user_handle": "The Cradle",
        "profile_image_url": "https://pbs.twimg.com/media/GZ9ccJvWYAAFA2h?format=jpg&name=360x360",
        "retweets": 315,
        "likes": 562,
        "tweet_images": [
            "https://pbs.twimg.com/media/GZ9ccJvWYAAFA2h?format=jpg&name=360x360"
        ],
        "tweet_videos": []
    },
    {
        "text": "살면서 손해보는 일이 없어야돼.. 그러므로 미국에서 “쌩라이브” 갈기는... 품격있는 ... 갓벽한 ... 제니 무대 봐야만 해... 아 어깨뽕..장착함.",
        "timestamp": "2024-10-16T09:22:10.000Z",
        "user_handle": "ᴅᴀʟᴘɪɴɢ",
        "profile_image_url": "",
        "retweets": 167,
        "likes": 548,
        "tweet_images": [],
        "tweet_videos": []
    },
    {
        "text": "[Notice] 24.10.17 Mnet 엠카운트다운 (사전녹화) 인원체크는 CJ ENM 센터 앞에서 진행됩니다! \n\n1차 인원체크(1순위 1~100): 9PM\n2차 인원체크(1순위 101~200): 9:40PM\n3차 인원체크(1순위 201~이외 순번): 10:20PM\n5순위 당일 신청자 : 10:50PM - 11PM\n\n#CNBLUE #씨엔블루 #X #엑스",
        "timestamp": "2024-10-16T11:43:09.000Z",
        "user_handle": "CNBLUE",
        "profile_image_url": "",
        "retweets": 143,
        "likes": 395,
        "tweet_images": [
            "https://pbs.twimg.com/media/GaAlnVLaYAASc3D?format=jpg&name=small"
        ],
        "tweet_videos": []
    },
    {
        "text": " Jhon Duran (20) scored off the bench yet again... this time for Colombia! ",
        "timestamp": "2024-10-16T11:30:01.000Z",
        "user_handle": "EuroFoot",
        "profile_image_url": "",
        "retweets": 81,
        "likes": 1600,
        "tweet_images": [],
        "tweet_videos": []
    },
    {
        "text": "ผมอุตส่าห์ทุ่มเทแต่เขาก็ไม่ให้ใจกลับมา | ดู #หนึ่งในร้อยEP7 คลิก https://ch3plus.com/v/230034\n\n#หนึ่งในร้อยEP8 คืนนี้ 20.30 น. \nดูสดออนไลน์ที่ #3Plus > https://bit.ly/3UclAU7 \n\n#หนึ่งในร้อย #MyCherieAmour \nทุกวันพุธ-พฤหัสบดี เวลา 20.30 น.",
        "timestamp": "2024-10-16T11:20:00.000Z",
        "user_handle": "3Plus",
        "profile_image_url": "",
        "retweets": 59,
        "likes": 122,
        "tweet_images": [],
        "tweet_videos": []
    },
    {
        "text": "『ゴジラｘコング 新たなる帝国』Blu-ray&DVD発売！\nこれを記念して、#モンアツ の #ゴジラxコング シリーズ撮り下ろしカット公開!!\n\n「S.H.MonsterArts SUKO & MOTHRA (2024) FROM GODZILLA × KONG: THE NEW EMPIRE」は #魂ウェブ商店 で10/20受注締切！\nhttps://p-bandai.jp/item/item-1000212188/…\n#GODZILLA #ゴジラ",
        "timestamp": "2024-10-16T12:00:10.000Z",
        "user_handle": "魂ネイションズ公式",
        "profile_image_url": "https://pbs.twimg.com/media/GaAhiZybIAAvbKZ?format=jpg&name=360x360",
        "retweets": 52,
        "likes": 154,
        "tweet_images": [
            "https://pbs.twimg.com/media/GaAhiZybIAAvbKZ?format=jpg&name=360x360",
            "https://pbs.twimg.com/media/GaAhirCbQAAPdek?format=jpg&name=360x360",
            "https://pbs.twimg.com/media/GaAhi9IbkAAOOmD?format=jpg&name=360x360"
        ],
        "tweet_videos": []
    },
    {
        "text": "本日2回配信予定です\n\n18:00〜\nCSファイナル初戦見る配信\n\n23:20〜\nプロスピ2024-2025発売最速プレイ配信\n\n※開始時間前後する可能性あり",
        "timestamp": "2024-10-16T06:02:00.000Z",
        "user_handle": "CLAY",
        "profile_image_url": "",
        "retweets": 26,
        "likes": 583,
        "tweet_images": [],
        "tweet_videos": []
    },
    {
        "text": "OUAIS ANNONCE CE SOIR A 20 H ! #KCORP",
        "timestamp": "2024-10-16T09:27:52.000Z",
        "user_handle": "KC Joman91 ",
        "profile_image_url": "",
        "retweets": 17,
        "likes": 424,
        "tweet_images": [],
        "tweet_videos": []
    },
    {
        "text": "OFFICIEL : Le film \"WALLACE & GROMIT: Vengeance Most Fowl\" sortira le 3 Janvier 2025 sur Netflix ! \n\nC'est le premier long-métrage de la licence depuis près de 20 ans, un premier TRAILER vient d'être révélé :",
        "timestamp": "2024-10-16T13:13:36.000Z",
        "user_handle": "Gaak.fr",
        "profile_image_url": "",
        "retweets": 15,
        "likes": 99,
        "tweet_images": [],
        "tweet_videos": []
    },
    {
        "text": " Cela dépend de la STRATÉGIE, elle peut sauver, stabiliser ou anéantir, ils sont 20 içi, en attendant le 21 ème, le Paris FC..?\n\n..SI votre CLUB est PRÉSENT sur cette carte c'est qu'il est actuellement sous régime de MULTIPROPRIÉTÉ. \n\nC'est à dire que son propriétaire est",
        "timestamp": "2024-10-16T07:54:48.000Z",
        "user_handle": "Météo Foot",
        "profile_image_url": "",
        "retweets": 14,
        "likes": 146,
        "tweet_images": [
            "https://pbs.twimg.com/media/GZ_xX7jWEAArZsD?format=jpg&name=small"
        ],
        "tweet_videos": []
    }
]